[
  {
    "name": "EEG A_01-REF",
    "location_orig": [
      3.6932396464004569,
      18.045141014517498,
      -6.3302006609560806
    ],
    "mask_dist": 3.9020875557928822,
    "mask_proj_pial_dist": 5.1422389655653769,
    "side": "r",
    "is_spiking": true,
    "is_spiking_comment": "",
    "is_scalp": false,
    "ROIids": [
      30,
      30,
      30,
      30
    ],
    "contact_type": "depth"
  },
  {
    "name": "EEG A_02-REF",
    "location_orig": [
      6.3960891386451806,
      19.936347846060158,
      -9.6230098190328022
    ],
    "mask_dist": 1.6488482453095465,
    "mask_proj_pial_dist": 3.1023670596750859,
    "side": "r",
    "is_spiking": true,
    "is_spiking_comment": "",
    "is_scalp": false,
    "ROIids": [
      30,
      30,
      30,
      30
    ],
    "contact_type": "depth"
  },
  {
    "name": "EEG A_03-REF",
    "location_orig": [
      9.5763801506191157,
      23.051945820921588,
      -12.041253874739027
    ],
    "mask_dist": 1.1253262379080307,
    "mask_proj_pial_dist": 0.66517090705961812,
    "side": "r",
    "is_spiking": true,
    "is_spiking_comment": "",
    "is_scalp": false,
    "ROIids": [
      30,
      30,
      30,
      30
    ],
    "contact_type": "depth"
  },
  {
    "name": "EEG A_04-REF",
    "location_orig": [
      17.531086359885023,
      26.692282857205356,
      -14.634410950919346
    ],
    "mask_dist": 0.66949569662617259,
    "mask_proj_pial_dist": null,
    "side": "r",
    "is_spiking": true,
    "is_spiking_comment": "",
    "is_scalp": false,
    "ROIids": [
      85,
      108,
      162,
      276
    ],
    "contact_type": "depth"
  },
  {
    "name": "EEG A_05-REF",
    "location_orig": [
      27.276198268135431,
      27.359098545429276,
      -15.828263863306773
    ],
    "mask_dist": 0.48449129200096164,
    "mask_proj_pial_dist": null,
    "side": "r",
    "is_spiking": true,
    "is_spiking_comment": "",
    "is_scalp": false,
    "ROIids": [
      85,
      108,
      162,
      276
    ],
    "contact_type": "depth"
  },
  {
    "name": "EEG A_06-REF",
    "location_orig": [
      37.140670556318156,
      28.200827254127319,
      -16.49737771427192
    ],
    "mask_dist": 0.55453075922554074,
    "mask_proj_pial_dist": null,
    "side": "r",
    "is_spiking": true,
    "is_spiking_comment": "",
    "is_scalp": false,
    "ROIids": [
      88,
      111,
      165,
      279
    ],
    "contact_type": "depth"
  },
  {
    "name": "EEG AC_01-REF",
    "location_orig": [
      -6.3728106407365033,
      40.270664491387095,
      23.15339671475067
    ],
    "mask_dist": 35.948645833849866,
    "mask_proj_pial_dist": null,
    "side": "r",
    "is_spiking": false,
    "is_spiking_comment": "",
    "is_scalp": false,
    "ROIids": [
      null,
      null,
      null,
      null
    ],
    "contact_type": "depth"
  },
  {
    "name": "EEG AC_02-REF",
    "location_orig": [
      -0.19474684713944157,
      41.644516496648436,
      23.15339671475067
    ],
    "mask_dist": 34.033724175683787,
    "mask_proj_pial_dist": null,
    "side": "r",
    "is_spiking": false,
    "is_spiking_comment": "",
    "is_scalp": false,
    "ROIids": [
      81,
      104,
      158,
      272
    ],
    "contact_type": "depth"
  },
  {
    "name": "EEG AC_03-REF",
    "location_orig": [
      5.7073397491319895,
      43.806774597366484,
      23.15339671475067
    ],
    "mask_dist": 33.336993264248896,
    "mask_proj_pial_dist": null,
    "side": "r",
    "is_spiking": false,
    "is_spiking_comment": "",
    "is_scalp": false,
    "ROIids": [
      81,
      104,
      158,
      272
    ],
    "contact_type": "depth"
  },
  {
    "name": "EEG AC_04-REF",
    "location_orig": [
      11.36350607055877,
      45.969032698084504,
      23.15339671475067
    ],
    "mask_dist": 33.531192811941231,
    "mask_proj_pial_dist": null,
    "side": "r",
    "is_spiking": false,
    "is_spiking_comment": "",
    "is_scalp": false,
    "ROIids": [
      26,
      26,
      26,
      26
    ],
    "contact_type": "depth"
  },
  {
    "name": "EEG AC_05-REF",
    "location_orig": [
      16.28191156745163,
      48.131290798802524,
      23.15339671475067
    ],
    "mask_dist": 30.256028648351702,
    "mask_proj_pial_dist": null,
    "side": "r",
    "is_spiking": false,
    "is_spiking_comment": "",
    "is_scalp": false,
    "ROIids": [
      null,
      null,
      null,
      null
    ],
    "contact_type": "depth"
  },
  {
    "name": "EEG AC_06-REF",
    "location_orig": [
      21.938077888878411,
      49.933172549400865,
      23.15339671475067
    ],
    "mask_dist": 26.808838965341792,
    "mask_proj_pial_dist": null,
    "side": "r",
    "is_spiking": false,
    "is_spiking_comment": "",
    "is_scalp": false,
    "ROIids": [
      99,
      122,
      176,
      290
    ],
    "contact_type": "depth"
  },
  {
    "name": "EEG AC_07-REF",
    "location_orig": [
      28.332005034839113,
      50.653925249640224,
      23.15339671475067
    ],
    "mask_dist": 23.250337090428552,
    "mask_proj_pial_dist": null,
    "side": "r",
    "is_spiking": false,
    "is_spiking_comment": "",
    "is_scalp": false,
    "ROIids": [
      99,
      122,
      176,
      290
    ],
    "contact_type": "depth"
  },
  {
    "name": "EEG AC_08-REF",
    "location_orig": [
      33.742251081421273,
      51.374677949879555,
      23.15339671475067
    ],
    "mask_dist": 21.367959679388246,
    "mask_proj_pial_dist": null,
    "side": "r",
    "is_spiking": false,
    "is_spiking_comment": "",
    "is_scalp": false,
    "ROIids": [
      106,
      129,
      240,
      435
    ],
    "contact_type": "depth"
  },
  {
    "name": "EEG AC_09-REF",
    "location_orig": [
      40.136178227381976,
      52.455807000238565,
      23.15339671475067
    ],
    "mask_dist": 20.840843831429794,
    "mask_proj_pial_dist": null,
    "side": "r",
    "is_spiking": false,
    "is_spiking_comment": "",
    "is_scalp": false,
    "ROIids": [
      99,
      122,
      223,
      388
    ],
    "contact_type": "depth"
  },
  {
    "name": "EEG AC_10-REF",
    "location_orig": [
      45.546424273964135,
      53.176559700477924,
      23.15339671475067
    ],
    "mask_dist": 20.755863871036489,
    "mask_proj_pial_dist": null,
    "side": "r",
    "is_spiking": false,
    "is_spiking_comment": "",
    "is_scalp": false,
    "ROIids": [
      99,
      122,
      223,
      388
    ],
    "contact_type": "depth"
  },
  {
    "name": "EEG AH_01-REF",
    "location_orig": [
      8.4442964173126143,
      15.61250511116765,
      -12.36358711705239
    ],
    "mask_dist": 0.76886481269244367,
    "mask_proj_pial_dist": 0.49136833338707414,
    "side": "r",
    "is_spiking": true,
    "is_spiking_comment": "",
    "is_scalp": false,
    "ROIids": [
      29,
      29,
      29,
      29
    ],
    "contact_type": "depth"
  },
  {
    "name": "EEG AH_02-REF",
    "location_orig": [
      13.344467353165385,
      15.327522100785842,
      -12.36358711705239
    ],
    "mask_dist": 0.59843518216086034,
    "mask_proj_pial_dist": null,
    "side": "r",
    "is_spiking": true,
    "is_spiking_comment": "",
    "is_scalp": false,
    "ROIids": [
      29,
      29,
      29,
      29
    ],
    "contact_type": "depth"
  },
  {
    "name": "EEG AH_03-REF",
    "location_orig": [
      18.366651121837833,
      15.327522100785842,
      -13.778378499786868
    ],
    "mask_dist": 0.53927881122768684,
    "mask_proj_pial_dist": null,
    "side": "r",
    "is_spiking": true,
    "is_spiking_comment": "",
    "is_scalp": false,
    "ROIids": [
      85,
      108,
      162,
      276
    ],
    "contact_type": "depth"
  },
  {
    "name": "EEG AH_04-REF",
    "location_orig": [
      28.211975226319225,
      16.045142793826813,
      -14.686712180478622
    ],
    "mask_dist": 0.38094926352427716,
    "mask_proj_pial_dist": null,
    "side": "r",
    "is_spiking": true,
    "is_spiking_comment": "",
    "is_scalp": false,
    "ROIids": [
      85,
      108,
      162,
      276
    ],
    "contact_type": "depth"
  },
  {
    "name": "EEG AH_05-REF",
    "location_orig": [
      37.800390322565363,
      17.139242940459667,
      -15.218566407578493
    ],
    "mask_dist": 0.32711138319398908,
    "mask_proj_pial_dist": null,
    "side": "r",
    "is_spiking": false,
    "is_spiking_comment": "",
    "is_scalp": false,
    "ROIids": [
      88,
      111,
      165,
      335
    ],
    "contact_type": "depth"
  },
  {
    "name": "EEG AH_06-REF",
    "location_orig": [
      47.2603509146939,
      17.856863633500637,
      -16.126900088270247
    ],
    "mask_dist": 0.32307438370258917,
    "mask_proj_pial_dist": null,
    "side": "r",
    "is_spiking": false,
    "is_spiking_comment": "",
    "is_scalp": false,
    "ROIids": [
      88,
      111,
      203,
      336
    ],
    "contact_type": "depth"
  },
  {
    "name": "EEG AI_01-REF",
    "location_orig": [
      31.744617237805642,
      47.2759802538275,
      5.1102466746003756
    ],
    "mask_dist": 8.4509652222551974,
    "mask_proj_pial_dist": null,
    "side": "r",
    "is_spiking": false,
    "is_spiking_comment": "",
    "is_scalp": false,
    "ROIids": [
      91,
      114,
      210,
      351
    ],
    "contact_type": "depth"
  },
  {
    "name": "EEG AI_02-REF",
    "location_orig": [
      31.412820643049884,
      46.820276217046796,
      11.463034040028276
    ],
    "mask_dist": 11.683198343214393,
    "mask_proj_pial_dist": 11.548413613338111,
    "side": "r",
    "is_spiking": true,
    "is_spiking_comment": "rare",
    "is_scalp": false,
    "ROIids": [
      91,
      114,
      210,
      351
    ],
    "contact_type": "depth"
  },
  {
    "name": "EEG AI_03-REF",
    "location_orig": [
      30.833209164244238,
      46.736294506340982,
      16.907939537281038
    ],
    "mask_dist": 15.756314600892164,
    "mask_proj_pial_dist": null,
    "side": "r",
    "is_spiking": false,
    "is_spiking_comment": "",
    "is_scalp": false,
    "ROIids": [
      99,
      122,
      176,
      386
    ],
    "contact_type": "depth"
  },
  {
    "name": "EEG AI_04-REF",
    "location_orig": [
      29.881875359363676,
      46.280590469560281,
      23.260726902708939
    ],
    "mask_dist": 21.291218839297645,
    "mask_proj_pial_dist": null,
    "side": "r",
    "is_spiking": false,
    "is_spiking_comment": "",
    "is_scalp": false,
    "ROIids": [
      99,
      122,
      176,
      290
    ],
    "contact_type": "depth"
  },
  {
    "name": "EEG AI_05-REF",
    "location_orig": [
      29.550078764607917,
      45.577071548729634,
      28.16090327905664
    ],
    "mask_dist": 25.368567868255191,
    "mask_proj_pial_dist": null,
    "side": "r",
    "is_spiking": false,
    "is_spiking_comment": "",
    "is_scalp": false,
    "ROIids": [
      99,
      122,
      176,
      290
    ],
    "contact_type": "depth"
  },
  {
    "name": "EEG AI_06-REF",
    "location_orig": [
      28.722652401752327,
      44.997460069923989,
      34.69526701811958
    ],
    "mask_dist": 31.409653537033069,
    "mask_proj_pial_dist": null,
    "side": "r",
    "is_spiking": false,
    "is_spiking_comment": "",
    "is_scalp": false,
    "ROIids": [
      106,
      129,
      240,
      434
    ],
    "contact_type": "depth"
  },
  {
    "name": "EEG AI_07-REF",
    "location_orig": [
      28.474837517702412,
      44.997460069923989,
      40.505710974440376
    ],
    "mask_dist": 36.87062364417023,
    "mask_proj_pial_dist": null,
    "side": "r",
    "is_spiking": false,
    "is_spiking_comment": "",
    "is_scalp": false,
    "ROIids": [
      106,
      129,
      240,
      433
    ],
    "contact_type": "depth"
  },
  {
    "name": "EEG AI_08-REF",
    "location_orig": [
      27.97920774960258,
      44.997460069923989,
      46.316154930761229
    ],
    "mask_dist": 42.353328740740423,
    "mask_proj_pial_dist": 41.6073888575482,
    "side": "r",
    "is_spiking": false,
    "is_spiking_comment": "",
    "is_scalp": false,
    "ROIids": [
      106,
      129,
      183,
      297
    ],
    "contact_type": "depth"
  },
  {
    "name": "EEG AI_09-REF",
    "location_orig": [
      27.731392865552664,
      44.997460069923989,
      53.034480755257164
    ],
    "mask_dist": 48.603277867280482,
    "mask_proj_pial_dist": null,
    "side": "r",
    "is_spiking": false,
    "is_spiking_comment": "",
    "is_scalp": false,
    "ROIids": [
      106,
      129,
      183,
      297
    ],
    "contact_type": "depth"
  },
  {
    "name": "EEG AI_10-REF",
    "location_orig": [
      27.544693864222211,
      44.462152974823027,
      58.559834503937793
    ],
    "mask_dist": 53.766342179737322,
    "mask_proj_pial_dist": 53.293637505418523,
    "side": "r",
    "is_spiking": false,
    "is_spiking_comment": "",
    "is_scalp": false,
    "ROIids": [
      106,
      129,
      183,
      297
    ],
    "contact_type": "depth"
  },
  {
    "name": "EEG HG_01-REF",
    "location_orig": [
      30.082493422987426,
      -0.64429459620075136,
      3.5070091359260118
    ],
    "mask_dist": 2.2980020329090003,
    "mask_proj_pial_dist": null,
    "side": "r",
    "is_spiking": false,
    "is_spiking_comment": "",
    "is_scalp": false,
    "ROIids": [
      29,
      29,
      29,
      29
    ],
    "contact_type": "depth"
  },
  {
    "name": "EEG HG_02-REF",
    "location_orig": [
      35.661822815533611,
      0.16646860567152544,
      2.6163961640437776
    ],
    "mask_dist": 5.7681663240498571,
    "mask_proj_pial_dist": null,
    "side": "r",
    "is_spiking": true,
    "is_spiking_comment": "",
    "is_scalp": false,
    "ROIids": [
      114,
      137,
      191,
      489
    ],
    "contact_type": "depth"
  },
  {
    "name": "EEG HG_03-REF",
    "location_orig": [
      41.612032485619011,
      0.59181264911012477,
      2.6163961640437776
    ],
    "mask_dist": 7.5327191706254712,
    "mask_proj_pial_dist": null,
    "side": "r",
    "is_spiking": true,
    "is_spiking_comment": "",
    "is_scalp": false,
    "ROIids": [
      109,
      132,
      257,
      472
    ],
    "contact_type": "depth"
  },
  {
    "name": "EEG HG_04-REF",
    "location_orig": [
      47.562242155704382,
      1.8678447794260364,
      2.6163961640437776
    ],
    "mask_dist": 8.5180007276343073,
    "mask_proj_pial_dist": null,
    "side": "r",
    "is_spiking": true,
    "is_spiking_comment": "",
    "is_scalp": false,
    "ROIids": [
      109,
      132,
      257,
      473
    ],
    "contact_type": "depth"
  },
  {
    "name": "EEG HG_05-REF",
    "location_orig": [
      53.512451825789753,
      2.0805168011453361,
      2.6163961640437776
    ],
    "mask_dist": 10.649509389186219,
    "mask_proj_pial_dist": null,
    "side": "r",
    "is_spiking": true,
    "is_spiking_comment": "",
    "is_scalp": false,
    "ROIids": [
      109,
      132,
      257,
      473
    ],
    "contact_type": "depth"
  },
  {
    "name": "EEG HG_06-REF",
    "location_orig": [
      59.462661495875125,
      2.2931888228646358,
      2.6163961640437776
    ],
    "mask_dist": 11.454853748723218,
    "mask_proj_pial_dist": null,
    "side": "r",
    "is_spiking": false,
    "is_spiking_comment": "",
    "is_scalp": false,
    "ROIids": [
      109,
      132,
      257,
      473
    ],
    "contact_type": "depth"
  },
  {
    "name": "EEG HG_07-REF",
    "location_orig": [
      65.024253136017251,
      2.2931888228646358,
      2.4408547532663079
    ],
    "mask_dist": 12.683385934464642,
    "mask_proj_pial_dist": 11.205277745107772,
    "side": "r",
    "is_spiking": true,
    "is_spiking_comment": "",
    "is_scalp": false,
    "ROIids": [
      94,
      147,
      218,
      371
    ],
    "contact_type": "depth"
  },
  {
    "name": "EEG HG_08-REF",
    "location_orig": [
      71.282454688754711,
      2.8912800030175845,
      2.4408547532663079
    ],
    "mask_dist": 14.550740850754128,
    "mask_proj_pial_dist": 10.637546052064575,
    "side": "r",
    "is_spiking": false,
    "is_spiking_comment": "",
    "is_scalp": false,
    "ROIids": [
      94,
      147,
      218,
      371
    ],
    "contact_type": "depth"
  },
  {
    "name": "EEG HG_09-REF",
    "location_orig": [
      77.37779142396414,
      2.8912800030175845,
      2.4408547532663079
    ],
    "mask_dist": 18.704170184283104,
    "mask_proj_pial_dist": 10.637546052064575,
    "side": "r",
    "is_spiking": false,
    "is_spiking_comment": "",
    "is_scalp": false,
    "ROIids": [
      94,
      147,
      218,
      371
    ],
    "contact_type": "depth"
  },
  {
    "name": "EEG HG_10-REF",
    "location_orig": [
      82.747492833553366,
      3.1039520247369126,
      2.4408547532663079
    ],
    "mask_dist": 22.987145358374779,
    "mask_proj_pial_dist": 9.5221493833374371,
    "side": "r",
    "is_spiking": false,
    "is_spiking_comment": "",
    "is_scalp": false,
    "ROIids": [
      94,
      147,
      218,
      371
    ],
    "contact_type": "depth"
  },
  {
    "name": "EEG OF_01-REF",
    "location_orig": [
      20.426919076817427,
      55.695689829654384,
      -2.4491985642346776
    ],
    "mask_dist": 13.478827419984572,
    "mask_proj_pial_dist": null,
    "side": "r",
    "is_spiking": false,
    "is_spiking_comment": "",
    "is_scalp": false,
    "ROIids": [
      91,
      144,
      211,
      354
    ],
    "contact_type": "depth"
  },
  {
    "name": "EEG OF_02-REF",
    "location_orig": [
      23.631755803606353,
      61.732787515139449,
      1.0065573951440001
    ],
    "mask_dist": 17.249139811367812,
    "mask_proj_pial_dist": null,
    "side": "r",
    "is_spiking": false,
    "is_spiking_comment": "",
    "is_scalp": false,
    "ROIids": [
      91,
      144,
      211,
      355
    ],
    "contact_type": "depth"
  },
  {
    "name": "EEG OF_03-REF",
    "location_orig": [
      24.329536163666319,
      63.977629967858434,
      7.7980784546547568
    ],
    "mask_dist": 22.768478683417751,
    "mask_proj_pial_dist": null,
    "side": "r",
    "is_spiking": false,
    "is_spiking_comment": "",
    "is_scalp": false,
    "ROIids": [
      91,
      144,
      211,
      355
    ],
    "contact_type": "depth"
  },
  {
    "name": "EEG OF_04-REF",
    "location_orig": [
      24.76510260971628,
      63.757661628883341,
      16.24912816700197
    ],
    "mask_dist": 28.053837277150823,
    "mask_proj_pial_dist": null,
    "side": "r",
    "is_spiking": true,
    "is_spiking_comment": "rare",
    "is_scalp": false,
    "ROIids": [
      106,
      152,
      243,
      441
    ],
    "contact_type": "depth"
  },
  {
    "name": "EEG OF_05-REF",
    "location_orig": [
      25.68285130875131,
      63.757661628883341,
      24.318448844874126
    ],
    "mask_dist": 32.383642627113254,
    "mask_proj_pial_dist": 32.014724012805139,
    "side": "r",
    "is_spiking": false,
    "is_spiking_comment": "",
    "is_scalp": false,
    "ROIids": [
      106,
      152,
      241,
      437
    ],
    "contact_type": "depth"
  },
  {
    "name": "EEG OF_06-REF",
    "location_orig": [
      26.118417754801271,
      65.74029016759232,
      31.878476635610809
    ],
    "mask_dist": 38.454543029093905,
    "mask_proj_pial_dist": null,
    "side": "r",
    "is_spiking": false,
    "is_spiking_comment": "",
    "is_scalp": false,
    "ROIids": [
      106,
      152,
      241,
      437
    ],
    "contact_type": "depth"
  },
  {
    "name": "EEG OF_07-REF",
    "location_orig": [
      26.118417754801271,
      67.591811749296284,
      39.404960845705489
    ],
    "mask_dist": 45.070391099378881,
    "mask_proj_pial_dist": null,
    "side": "r",
    "is_spiking": false,
    "is_spiking_comment": "",
    "is_scalp": false,
    "ROIids": [
      106,
      152,
      241,
      437
    ],
    "contact_type": "depth"
  },
  {
    "name": "EEG OF_08-REF",
    "location_orig": [
      25.478907153410205,
      68.4284969943838,
      48.468458518252021
    ],
    "mask_dist": 52.9040088480923,
    "mask_proj_pial_dist": 47.687025906475561,
    "side": "r",
    "is_spiking": false,
    "is_spiking_comment": "",
    "is_scalp": false,
    "ROIids": [
      106,
      129,
      183,
      438
    ],
    "contact_type": "depth"
  },
  {
    "name": "EEG OF_09-REF",
    "location_orig": [
      25.478907153410205,
      69.493376834057756,
      54.65005594870135
    ],
    "mask_dist": 58.582212674755759,
    "mask_proj_pial_dist": 52.4496237658272,
    "side": "r",
    "is_spiking": false,
    "is_spiking_comment": "",
    "is_scalp": false,
    "ROIids": [
      106,
      129,
      183,
      438
    ],
    "contact_type": "depth"
  },
  {
    "name": "EEG OF_10-REF",
    "location_orig": [
      25.478907153410205,
      70.542232490097774,
      62.142996578154055
    ],
    "mask_dist": 65.504525925974164,
    "mask_proj_pial_dist": 53.806110556736364,
    "side": "r",
    "is_spiking": false,
    "is_spiking_comment": "",
    "is_scalp": false,
    "ROIids": [
      106,
      129,
      183,
      438
    ],
    "contact_type": "depth"
  },
  {
    "name": "EEG PC_01-REF",
    "location_orig": [
      -0.47696362411460314,
      -16.134315774505126,
      20.400216764843606
    ],
    "mask_dist": 18.770534022883947,
    "mask_proj_pial_dist": null,
    "side": "r",
    "is_spiking": false,
    "is_spiking_comment": "",
    "is_scalp": false,
    "ROIids": [
      null,
      null,
      null,
      null
    ],
    "contact_type": "depth"
  },
  {
    "name": "EEG PC_02-REF",
    "location_orig": [
      7.3526731161470877,
      -18.4849177452071,
      20.400216764843606
    ],
    "mask_dist": 15.595434693288686,
    "mask_proj_pial_dist": null,
    "side": "r",
    "is_spiking": false,
    "is_spiking_comment": "",
    "is_scalp": false,
    "ROIids": [
      null,
      null,
      null,
      null
    ],
    "contact_type": "depth"
  },
  {
    "name": "EEG PC_03-REF",
    "location_orig": [
      15.18230985640875,
      -20.750457819919362,
      22.744865399682624
    ],
    "mask_dist": 18.014008782981332,
    "mask_proj_pial_dist": null,
    "side": "r",
    "is_spiking": false,
    "is_spiking_comment": "",
    "is_scalp": false,
    "ROIids": [
      null,
      null,
      null,
      null
    ],
    "contact_type": "depth"
  },
  {
    "name": "EEG PC_04-REF",
    "location_orig": [
      21.812936845748368,
      -24.092337716495976,
      22.744865399682624
    ],
    "mask_dist": 19.719415086072203,
    "mask_proj_pial_dist": null,
    "side": "r",
    "is_spiking": false,
    "is_spiking_comment": "",
    "is_scalp": false,
    "ROIids": [
      104,
      127,
      236,
      423
    ],
    "contact_type": "depth"
  },
  {
    "name": "EEG PC_05-REF",
    "location_orig": [
      29.433004546450576,
      -26.442939687197949,
      25.089514034521642
    ],
    "mask_dist": 23.456073929976469,
    "mask_proj_pial_dist": null,
    "side": "r",
    "is_spiking": false,
    "is_spiking_comment": "",
    "is_scalp": false,
    "ROIids": [
      87,
      110,
      164,
      278
    ],
    "contact_type": "depth"
  },
  {
    "name": "EEG PC_06-REF",
    "location_orig": [
      36.743872024851953,
      -28.793541657899922,
      25.621730609590855
    ],
    "mask_dist": 27.537647761102878,
    "mask_proj_pial_dist": null,
    "side": "r",
    "is_spiking": true,
    "is_spiking_comment": "rare",
    "is_scalp": false,
    "ROIids": [
      87,
      110,
      164,
      278
    ],
    "contact_type": "depth"
  },
  {
    "name": "EEG PC_07-REF",
    "location_orig": [
      44.302099681094006,
      -30.776097509649176,
      25.621730609590855
    ],
    "mask_dist": 32.20119354103506,
    "mask_proj_pial_dist": null,
    "side": "r",
    "is_spiking": true,
    "is_spiking_comment": "rare",
    "is_scalp": false,
    "ROIids": [
      87,
      110,
      198,
      326
    ],
    "contact_type": "depth"
  },
  {
    "name": "EEG PC_08-REF",
    "location_orig": [
      51.104504571711914,
      -33.494745599303883,
      25.621730609590855
    ],
    "mask_dist": 37.789729317618153,
    "mask_proj_pial_dist": null,
    "side": "r",
    "is_spiking": false,
    "is_spiking_comment": "",
    "is_scalp": false,
    "ROIids": [
      87,
      110,
      198,
      326
    ],
    "contact_type": "depth"
  },
  {
    "name": "EEG PC_09-REF",
    "location_orig": [
      58.834510129232257,
      -35.760285674016146,
      25.621730609590855
    ],
    "mask_dist": 44.253499610515455,
    "mask_proj_pial_dist": 42.701307599533948,
    "side": "r",
    "is_spiking": false,
    "is_spiking_comment": "",
    "is_scalp": false,
    "ROIids": [
      87,
      110,
      198,
      326
    ],
    "contact_type": "depth"
  },
  {
    "name": "EEG PC_10-REF",
    "location_orig": [
      66.763778052235267,
      -37.657779629775675,
      27.51327122948743
    ],
    "mask_dist": 51.509128137885881,
    "mask_proj_pial_dist": 44.653111676523828,
    "side": "r",
    "is_spiking": false,
    "is_spiking_comment": "",
    "is_scalp": false,
    "ROIids": [
      87,
      110,
      198,
      326
    ],
    "contact_type": "depth"
  },
  {
    "name": "EEG PH_01-REF",
    "location_orig": [
      15.39894368318096,
      4.8619950681300281,
      -10.709772683953247
    ],
    "mask_dist": 0.51228370334959961,
    "mask_proj_pial_dist": 0.51766727859505413,
    "side": "r",
    "is_spiking": true,
    "is_spiking_comment": "",
    "is_scalp": false,
    "ROIids": [
      95,
      118,
      172,
      376
    ],
    "contact_type": "depth"
  },
  {
    "name": "EEG PH_02-REF",
    "location_orig": [
      20.519828170962825,
      4.0271907420054163,
      -9.8775875337781827
    ],
    "mask_dist": 0.49627292250443877,
    "mask_proj_pial_dist": null,
    "side": "r",
    "is_spiking": true,
    "is_spiking_comment": "",
    "is_scalp": false,
    "ROIids": [
      95,
      118,
      172,
      376
    ],
    "contact_type": "depth"
  },
  {
    "name": "EEG PH_03-REF",
    "location_orig": [
      25.504679717805971,
      3.3917317312782984,
      -9.44409301439805
    ],
    "mask_dist": 0.77201819872653166,
    "mask_proj_pial_dist": null,
    "side": "r",
    "is_spiking": true,
    "is_spiking_comment": "",
    "is_scalp": false,
    "ROIids": [
      29,
      29,
      29,
      29
    ],
    "contact_type": "depth"
  },
  {
    "name": "EEG PH_04-REF",
    "location_orig": [
      34.594450512194442,
      1.9588914589612614,
      -8.157567225130208
    ],
    "mask_dist": 0.43701747928533957,
    "mask_proj_pial_dist": null,
    "side": "r",
    "is_spiking": true,
    "is_spiking_comment": "",
    "is_scalp": false,
    "ROIids": [
      88,
      111,
      203,
      337
    ],
    "contact_type": "depth"
  },
  {
    "name": "EEG PH_05-REF",
    "location_orig": [
      44.483476935677459,
      -0.00064054188817408431,
      -6.9672705594578588
    ],
    "mask_dist": 3.9161902512359976,
    "mask_proj_pial_dist": null,
    "side": "r",
    "is_spiking": true,
    "is_spiking_comment": "",
    "is_scalp": false,
    "ROIids": [
      88,
      111,
      203,
      337
    ],
    "contact_type": "depth"
  },
  {
    "name": "EEG PH_06-REF",
    "location_orig": [
      54.160286076956282,
      -1.7102203981142168,
      -6.2533840843453845
    ],
    "mask_dist": 7.1631417346383781,
    "mask_proj_pial_dist": null,
    "side": "r",
    "is_spiking": true,
    "is_spiking_comment": "",
    "is_scalp": false,
    "ROIids": [
      94,
      147,
      218,
      371
    ],
    "contact_type": "depth"
  },
  {
    "name": "EEG PI_01-REF",
    "location_orig": [
      36.240215075768248,
      -2.9088780379588,
      6.8314887924708785
    ],
    "mask_dist": 7.1899398869390483,
    "mask_proj_pial_dist": null,
    "side": "r",
    "is_spiking": false,
    "is_spiking_comment": "",
    "is_scalp": false,
    "ROIids": [
      109,
      132,
      257,
      472
    ],
    "contact_type": "depth"
  },
  {
    "name": "EEG PI_02-REF",
    "location_orig": [
      36.240215075768248,
      -6.9684024489458523,
      13.693920860199825
    ],
    "mask_dist": 10.892748708754139,
    "mask_proj_pial_dist": null,
    "side": "r",
    "is_spiking": false,
    "is_spiking_comment": "",
    "is_scalp": false,
    "ROIids": [
      109,
      132,
      186,
      300
    ],
    "contact_type": "depth"
  },
  {
    "name": "EEG PI_03-REF",
    "location_orig": [
      36.240215075768248,
      -10.704609693931474,
      20.650695322729177
    ],
    "mask_dist": 16.486672266883446,
    "mask_proj_pial_dist": null,
    "side": "r",
    "is_spiking": false,
    "is_spiking_comment": "",
    "is_scalp": false,
    "ROIids": [
      110,
      159,
      263,
      488
    ],
    "contact_type": "depth"
  },
  {
    "name": "EEG PI_04-REF",
    "location_orig": [
      36.240215075768248,
      -14.393754846258076,
      27.482531239611035
    ],
    "mask_dist": 22.72516826543967,
    "mask_proj_pial_dist": null,
    "side": "r",
    "is_spiking": false,
    "is_spiking_comment": "",
    "is_scalp": false,
    "ROIids": [
      110,
      159,
      263,
      487
    ],
    "contact_type": "depth"
  },
  {
    "name": "EEG PI_05-REF",
    "location_orig": [
      37.210217096684715,
      -18.147634603253323,
      34.659195682570441
    ],
    "mask_dist": 30.180968218178869,
    "mask_proj_pial_dist": null,
    "side": "r",
    "is_spiking": false,
    "is_spiking_comment": "",
    "is_scalp": false,
    "ROIids": [
      108,
      131,
      185,
      299
    ],
    "contact_type": "depth"
  },
  {
    "name": "EEG PI_06-REF",
    "location_orig": [
      37.210217096684715,
      -22.30740068217014,
      41.835860125529848
    ],
    "mask_dist": 37.706924817173572,
    "mask_proj_pial_dist": null,
    "side": "r",
    "is_spiking": false,
    "is_spiking_comment": "",
    "is_scalp": false,
    "ROIids": [
      108,
      131,
      185,
      299
    ],
    "contact_type": "depth"
  },
  {
    "name": "EEG PI_07-REF",
    "location_orig": [
      37.756660283669987,
      -25.525924907906528,
      48.7278999833905
    ],
    "mask_dist": 45.083220218389847,
    "mask_proj_pial_dist": null,
    "side": "r",
    "is_spiking": false,
    "is_spiking_comment": "",
    "is_scalp": false,
    "ROIids": [
      108,
      131,
      185,
      299
    ],
    "contact_type": "depth"
  },
  {
    "name": "EEG PI_08-REF",
    "location_orig": [
      37.756660283669987,
      -30.127551745677493,
      54.930282789096111
    ],
    "mask_dist": 52.259421000316273,
    "mask_proj_pial_dist": null,
    "side": "r",
    "is_spiking": false,
    "is_spiking_comment": "",
    "is_scalp": false,
    "ROIids": [
      108,
      131,
      185,
      459
    ],
    "contact_type": "depth"
  },
  {
    "name": "EEG PI_09-REF",
    "location_orig": [
      37.756660283669987,
      -33.65720869510406,
      61.1371962584916
    ],
    "mask_dist": 59.157781643988024,
    "mask_proj_pial_dist": 56.653137687023836,
    "side": "r",
    "is_spiking": false,
    "is_spiking_comment": "",
    "is_scalp": false,
    "ROIids": [
      108,
      131,
      185,
      459
    ],
    "contact_type": "depth"
  },
  {
    "name": "EEG PI_10-REF",
    "location_orig": [
      37.756660283669987,
      -36.951555181235534,
      66.3096241496545
    ],
    "mask_dist": 65.086310963678059,
    "mask_proj_pial_dist": 57.460281187864958,
    "side": "r",
    "is_spiking": false,
    "is_spiking_comment": "",
    "is_scalp": false,
    "ROIids": [
      108,
      156,
      252,
      463
    ],
    "contact_type": "depth"
  }
]